integrations/_infra/Dockerfile.Deb
integrations/_infra/Dockerfile.alpine
integrations/_infra/Dockerfile.base.builder
integrations/_infra/Dockerfile.base.runner
integrations/_infra/Dockerfile.dockerignore
integrations/_infra/Dockerfile.local
integrations/_infra/Makefile
integrations/_infra/README.md
integrations/_infra/entry_local.sh
integrations/_infra/grpcio.sh
integrations/_infra/hosts
integrations/_infra/init.sh
integrations/_infra/sync_ca_certs.sh
port_ocean/__init__.py
port_ocean/bootstrap.py
port_ocean/cache/__init__.py
port_ocean/cache/base.py
port_ocean/cache/disk.py
port_ocean/cache/errors.py
port_ocean/cache/memory.py
port_ocean/cli/__init__.py
port_ocean/cli/cli.py
port_ocean/cli/commands/__init__.py
port_ocean/cli/commands/defaults/__init___.py
port_ocean/cli/commands/defaults/clean.py
port_ocean/cli/commands/defaults/dock.py
port_ocean/cli/commands/defaults/group.py
port_ocean/cli/commands/list_integrations.py
port_ocean/cli/commands/main.py
port_ocean/cli/commands/new.py
port_ocean/cli/commands/pull.py
port_ocean/cli/commands/sail.py
port_ocean/cli/commands/version.py
port_ocean/cli/cookiecutter/__init__.py
port_ocean/cli/cookiecutter/cookiecutter.json
port_ocean/cli/cookiecutter/extensions.py
port_ocean/cli/cookiecutter/hooks/post_gen_project.py
port_ocean/cli/cookiecutter/{{cookiecutter.integration_slug}}/.env.development
port_ocean/cli/cookiecutter/{{cookiecutter.integration_slug}}/.env.example
port_ocean/cli/cookiecutter/{{cookiecutter.integration_slug}}/.gitignore
port_ocean/cli/cookiecutter/{{cookiecutter.integration_slug}}/.port/resources/.gitignore
port_ocean/cli/cookiecutter/{{cookiecutter.integration_slug}}/.port/resources/blueprints.json
port_ocean/cli/cookiecutter/{{cookiecutter.integration_slug}}/.port/resources/port-app-config.yml
port_ocean/cli/cookiecutter/{{cookiecutter.integration_slug}}/.port/spec.yaml
port_ocean/cli/cookiecutter/{{cookiecutter.integration_slug}}/CHANGELOG.md
port_ocean-0.35.2.dist-info/LICENSE.md
port_ocean-0.35.2.dist-info/METADATA
port_ocean-0.35.2.dist-info/WHEEL
port_ocean-0.35.2.dist-info/entry_points.txt
port_ocean-0.35.2.dist-info/RECORD
