Metadata-Version: 2.1
Name: port-ocean
Version: 0.35.2
Summary: Port Ocean is a CLI tool for managing your Port projects.
Home-page: https://app.getport.io
Keywords: ocean,port-ocean,port
Author: Daniel Sinai
Author-email: daniel@getport.io
Requires-Python: >=3.12,<4.0
Classifier: Framework :: FastAPI
Classifier: Intended Audience :: Developers
Classifier: License :: OSI Approved :: Apache Software License
Classifier: Natural Language :: English
Classifier: Operating System :: POSIX
Classifier: Programming Language :: Python
Classifier: Programming Language :: Python :: 3
Classifier: Programming Language :: Python :: 3.12
Classifier: Programming Language :: Python :: 3.13
Classifier: Programming Language :: Python :: 3.11
Classifier: Topic :: Software Development :: Libraries
Classifier: Topic :: Software Development :: Libraries :: Application Frameworks
Classifier: Topic :: Software Development :: Libraries :: Python Modules
Classifier: Topic :: Utilities
Provides-Extra: cli
Requires-Dist: aiofiles (>=24.1.0,<25.0.0)
Requires-Dist: aiostream (>=0.5.2,<0.7.0)
Requires-Dist: click (>=8.1.3,<9.0.0) ; extra == "cli"
Requires-Dist: confluent-kafka (>=2.10.1,<3.0.0)
Requires-Dist: cookiecutter (>=2.1.1,<3.0.0) ; extra == "cli"
Requires-Dist: cryptography (>=44.0.1,<45.0.0)
Requires-Dist: fastapi (>=0.121.0,<0.122.0)
Requires-Dist: httpx (>=0.28.1,<0.29.0)
Requires-Dist: ijson (>=3.4.0,<4.0.0)
Requires-Dist: jinja2 (>=3.1.6)
Requires-Dist: jinja2-time (>=0.2.0,<0.3.0) ; extra == "cli"
Requires-Dist: jmespath (>=1.0.1,<2.0.0)
Requires-Dist: jq (>=1.8.0,<2.0.0)
Requires-Dist: loguru (>=0.7.0,<0.8.0)
Requires-Dist: prometheus-client (>=0.21.1,<0.22.0)
Requires-Dist: psutil (>=7.2.1,<8.0.0)
Requires-Dist: pydantic[dotenv] (>=1.10.8,<2.0.0)
Requires-Dist: pydispatcher (>=2.0.7,<3.0.0)
Requires-Dist: pyhumps (>=3.8.0,<4.0.0)
Requires-Dist: pyjwt (>=2.10.1,<3.0.0)
Requires-Dist: pytest-cov (>=6.0.0,<7.0.0)
Requires-Dist: python-dateutil (>=2.9.0.post0,<3.0.0)
Requires-Dist: pyyaml (>=6.0,<7.0)
Requires-Dist: rich (>=13.4.1,<14.0.0) ; extra == "cli"
Requires-Dist: six (>=1.16.0,<2.0.0)
Requires-Dist: tomli (>=2.0.1,<3.0.0)
Requires-Dist: urllib3 (>=2.6.3,<3.0.0)
Requires-Dist: uvicorn (>=0.34.3,<0.35.0)
Requires-Dist: werkzeug (>=2.3.4,<4.0.0)
Project-URL: Repository, https://github.com/port-labs/Port-Ocean
